pytorch_drl/__init__.py
pytorch_drl/agent/__init__.py
pytorch_drl/agent/base_agent.py
pytorch_drl/agent/model_free.py
pytorch_drl/agents/__init__.py
pytorch_drl/agents/base_agent.py
pytorch_drl/env/__init__.py
pytorch_drl/env/base_env.py
pytorch_drl/env/gym_env.py
pytorch_drl/environments/__init__.py
pytorch_drl/net/__init__.py
pytorch_drl/net/base_net.py
pytorch_drl/net/discrete.py
pytorch_drl/trainer/__init__.py
pytorch_drl/trainer/base_trainer.py
pytorch_drl/trainer/off_policy.py
pytorch_drl/utils/__init__.py
pytorch_drl/utils/buffer.py
PyTorch_DRL-0.0.2.dist-info/METADATA
PyTorch_DRL-0.0.2.dist-info/WHEEL
PyTorch_DRL-0.0.2.dist-info/top_level.txt
PyTorch_DRL-0.0.2.dist-info/RECORD
